esp8266/__init__.py
esp8266.py-0.0.3.dist-info/METADATA
esp8266.py-0.0.3.dist-info/RECORD
esp8266.py-0.0.3.dist-info/WHEEL
esp8266.py-0.0.3.dist-info/top_level.txt
