Metadata-Version: 2.1
Name: esp8266.py
Version: 0.0.3
Summary: ESP8266 python library, a wrapper for AT commands (Hayes command set) using UART serial.
Home-page: https://github.com/muchrooms/esp8266.py
Author: letli
Author-email: letli@74ls74.org
License: UNKNOWN
Platform: UNKNOWN
Classifier: Programming Language :: Python :: 2
Classifier: Programming Language :: Python :: 3
Classifier: License :: OSI Approved :: MIT License
Classifier: Operating System :: OS Independent
Requires-Dist: pySerial (>=3.0)
